views_transformation_library/__init__.py
views_transformation_library/fourier_lag.py
views_transformation_library/identity.py
views_transformation_library/missing.py
views_transformation_library/multi_column.py
views_transformation_library/spacetime_distance.py
views_transformation_library/spatial_tree.py
views_transformation_library/splag4d.py
views_transformation_library/splag_country.py
views_transformation_library/temporal_entropy.py
views_transformation_library/temporal_tree.py
views_transformation_library/tlag3d.py
views_transformation_library/utilities.py
views_transformation_library/views_2.py
views_transformation_library-2.7.2.dist-info/LICENSE
views_transformation_library-2.7.2.dist-info/METADATA
views_transformation_library-2.7.2.dist-info/WHEEL
views_transformation_library-2.7.2.dist-info/RECORD
