Metadata-Version: 2.1
Name: views-transformation-library
Version: 2.7.2
Summary: A package containing data transformation functions used by the ViEWS team
Home-page: https://www.github.com/prio-data/views_transformation_library
License: CC-BY-NC
Author: peder2911
Author-email: pglandsverk@gmail.com
Requires-Python: >=3.8
Classifier: License :: Other/Proprietary License
Classifier: Programming Language :: Python :: 3
Classifier: Programming Language :: Python :: 3.8
Classifier: Programming Language :: Python :: 3.9
Classifier: Programming Language :: Python :: 3.10
Classifier: Programming Language :: Python :: 3.11
Classifier: Programming Language :: Python :: 3.12
Requires-Dist: ingester3 (>=0.6.0)
Requires-Dist: pandas (>=1.2.3,<2.0.0)
Requires-Dist: scikit_learn (>=1.0.2,<2.0.0)
Requires-Dist: scipy (>=1.6.2,<2.0.0)
Requires-Dist: stepshift (>=1.2.0)
Requires-Dist: xarray (>=0.19.0)
